.eslintignore
.eslintrc.js
.flake8
.gitignore
.gitlab-ci.yml
LICENSE
MANIFEST.in
README.md
setup.cfg
setup.py
gramexenterprise/__init__.py
gramexenterprise.egg-info/PKG-INFO
gramexenterprise.egg-info/SOURCES.txt
gramexenterprise.egg-info/dependency_links.txt
gramexenterprise.egg-info/not-zip-safe
gramexenterprise.egg-info/requires.txt
gramexenterprise.egg-info/top_level.txt
gramexenterprise/handlers/__init__.py
gramexenterprise/handlers/auth.email.template.html
gramexenterprise/handlers/auth.sms.template.html
gramexenterprise/handlers/authhandler.py
gramexenterprise/handlers/forgot.template.html
gramexenterprise/handlers/signup.template.html