Metadata-Version: 2.1
Name: gramexenterprise
Version: 1.93.1
Summary: Gramex: Visual Analytics Platform (Enterprise version)
Home-page: http://gramener.com/gramex/guide/
Author: Gramener
Author-email: s.anand@gramener.com
License: Other/Proprietary License
Keywords: gramex
Classifier: Development Status :: 5 - Production/Stable
Classifier: Intended Audience :: Developers
Classifier: License :: Other/Proprietary License
Classifier: Natural Language :: English
Classifier: Programming Language :: Python :: 3
Classifier: Programming Language :: Python :: 3.6
Classifier: Programming Language :: Python :: 3.7
License-File: LICENSE
